simple_jquery_django_auto_logout/__init__.py
simple_jquery_django_auto_logout/context_processors.py
simple_jquery_django_auto_logout/supports.py
simple_jquery_django_auto_logout-1.0.1.dist-info/LICENSE.txt
simple_jquery_django_auto_logout-1.0.1.dist-info/METADATA
simple_jquery_django_auto_logout-1.0.1.dist-info/WHEEL
simple_jquery_django_auto_logout-1.0.1.dist-info/top_level.txt
simple_jquery_django_auto_logout-1.0.1.dist-info/RECORD
