Metadata-Version: 2.1
Name: simple_jquery_django_auto_logout
Version: 1.0.1
Summary: Simple Jquery-Django autologout system
Home-page: https://gitlab.com/adityayudhi/simple_jquery_django_auto_logout
Author: Aditya Yudhi Hanafi
Author-email: adityayudhi10@gmail.com
Project-URL: Bug Tracker, https://gitlab.com/adityayudhi/simple_jquery_django_auto_logout/-/issues
Project-URL: repository, https://gitlab.com/adityayudhi/simple_jquery_django_auto_logout
Classifier: Programming Language :: Python :: 3
Classifier: License :: OSI Approved :: MIT License
Classifier: Operating System :: OS Independent
Requires-Python: >=3.6
License-File: LICENSE.txt
